video_editor_mcp/__init__.py
video_editor_mcp/edit.json
video_editor_mcp/generate_charts.py
video_editor_mcp/generate_opentimeline.py
video_editor_mcp/search_local_videos.py
video_editor_mcp/server.py
iflow_mcp_video_editor_mcp-0.1.62.dist-info/METADATA
iflow_mcp_video_editor_mcp-0.1.62.dist-info/WHEEL
iflow_mcp_video_editor_mcp-0.1.62.dist-info/entry_points.txt
iflow_mcp_video_editor_mcp-0.1.62.dist-info/RECORD
