Metadata-Version: 2.4
Name: iflow-mcp_video-editor-mcp
Version: 0.1.62
Summary: Video Jungle MCP Server for Adding, Analysing, Searching, and Editing Videos
Project-URL: Homepage, https://github.com/burningion/video-editing-mcp
Project-URL: Issues, https://github.com/burningion/video-editing-mcp/issues
Author-email: Kirk Kaiser <kirk@zothcorp.com>
Requires-Python: >=3.11
Requires-Dist: einops>=0.8.0
Requires-Dist: manim>=0.18.1
Requires-Dist: mcp>=1.6.0
Requires-Dist: numpy>=2.2.2
Requires-Dist: opentimelineio>=0.17.0
Requires-Dist: osxphotos>=0.69.2
Requires-Dist: pillow>=11.0.0
Requires-Dist: requests>=2.32.3
Requires-Dist: thefuzz>=0.22.1
Requires-Dist: timm>=1.0.12
Requires-Dist: torch>=2.2
Requires-Dist: torchvision>=0.20.1
Requires-Dist: transformers[torch]==4.47.1
Requires-Dist: videojungle>=0.1.79
